mdnewline/__init__.py
mdnewline/cli.py
mdnewline/processor.py
mdnewline-0.1.3.dist-info/licenses/LICENSE
mdnewline-0.1.3.dist-info/METADATA
mdnewline-0.1.3.dist-info/WHEEL
mdnewline-0.1.3.dist-info/entry_points.txt
mdnewline-0.1.3.dist-info/top_level.txt
mdnewline-0.1.3.dist-info/RECORD
