Metadata-Version: 2.4
Name: mdnewline
Version: 0.1.3
Summary: Command line tool to add line breaks after sentences in markdown files for better git diffs
Author-email: Russell Poldrack <poldrack@gmail.com>
License-Expression: MIT
Project-URL: Repository, https://github.com/poldrack/mdnewline.git
Classifier: Development Status :: 4 - Beta
Requires-Python: >=3.12
License-File: LICENSE
Requires-Dist: pytest>=8.4.1
Dynamic: license-file
